relatively/__init__.py
relatively/relatively.py
relatively-1.0.6.dist-info/LICENSE
relatively-1.0.6.dist-info/METADATA
relatively-1.0.6.dist-info/WHEEL
relatively-1.0.6.dist-info/top_level.txt
relatively-1.0.6.dist-info/RECORD
